{
  "type": "Program",
  "start": 0,
  "end": 396,
  "loc": {
    "start": {
      "line": 1,
      "column": 0
    },
    "end": {
      "line": 23,
      "column": 0
    }
  },
  "sourceType": "module",
  "body": [
    {
      "type": "ImportDeclaration",
      "start": 0,
      "end": 46,
      "loc": {
        "start": {
          "line": 1,
          "column": 0
        },
        "end": {
          "line": 1,
          "column": 46
        }
      },
      "specifiers": [
        {
          "type": "ImportSpecifier",
          "start": 9,
          "end": 17,
          "loc": {
            "start": {
              "line": 1,
              "column": 9
            },
            "end": {
              "line": 1,
              "column": 17
            }
          },
          "imported": {
            "type": "Identifier",
            "start": 9,
            "end": 17,
            "loc": {
              "start": {
                "line": 1,
                "column": 9
              },
              "end": {
                "line": 1,
                "column": 17
              }
            },
            "name": "Business"
          },
          "local": {
            "type": "Identifier",
            "start": 9,
            "end": 17,
            "loc": {
              "start": {
                "line": 1,
                "column": 9
              },
              "end": {
                "line": 1,
                "column": 17
              }
            },
            "name": "Business"
          }
        }
      ],
      "importKind": "value",
      "source": {
        "type": "Literal",
        "start": 25,
        "end": 45,
        "loc": {
          "start": {
            "line": 1,
            "column": 25
          },
          "end": {
            "line": 1,
            "column": 45
          }
        },
        "value": "../../../../models",
        "rawValue": "../../../../models",
        "raw": "'../../../../models'"
      }
    },
    {
      "type": "ExportNamedDeclaration",
      "start": 49,
      "end": 373,
      "loc": {
        "start": {
          "line": 4,
          "column": 0
        },
        "end": {
          "line": 19,
          "column": 1
        }
      },
      "declaration": {
        "type": "FunctionDeclaration",
        "start": 56,
        "end": 373,
        "loc": {
          "start": {
            "line": 4,
            "column": 7
          },
          "end": {
            "line": 19,
            "column": 1
          }
        },
        "id": {
          "type": "Identifier",
          "start": 71,
          "end": 74,
          "loc": {
            "start": {
              "line": 4,
              "column": 22
            },
            "end": {
              "line": 4,
              "column": 25
            }
          },
          "name": "del"
        },
        "generator": false,
        "expression": false,
        "async": true,
        "params": [
          {
            "type": "Identifier",
            "start": 75,
            "end": 78,
            "loc": {
              "start": {
                "line": 4,
                "column": 26
              },
              "end": {
                "line": 4,
                "column": 29
              }
            },
            "name": "ctx"
          }
        ],
        "body": {
          "type": "BlockStatement",
          "start": 80,
          "end": 373,
          "loc": {
            "start": {
              "line": 4,
              "column": 31
            },
            "end": {
              "line": 19,
              "column": 1
            }
          },
          "body": [
            {
              "type": "VariableDeclaration",
              "start": 84,
              "end": 122,
              "loc": {
                "start": {
                  "line": 5,
                  "column": 2
                },
                "end": {
                  "line": 5,
                  "column": 40
                }
              },
              "declarations": [
                {
                  "type": "VariableDeclarator",
                  "start": 90,
                  "end": 121,
                  "loc": {
                    "start": {
                      "line": 5,
                      "column": 8
                    },
                    "end": {
                      "line": 5,
                      "column": 39
                    }
                  },
                  "id": {
                    "type": "ObjectPattern",
                    "start": 90,
                    "end": 104,
                    "loc": {
                      "start": {
                        "line": 5,
                        "column": 8
                      },
                      "end": {
                        "line": 5,
                        "column": 22
                      }
                    },
                    "properties": [
                      {
                        "type": "Property",
                        "start": 92,
                        "end": 102,
                        "loc": {
                          "start": {
                            "line": 5,
                            "column": 10
                          },
                          "end": {
                            "line": 5,
                            "column": 20
                          }
                        },
                        "method": false,
                        "shorthand": true,
                        "computed": false,
                        "key": {
                          "type": "Identifier",
                          "start": 92,
                          "end": 102,
                          "loc": {
                            "start": {
                              "line": 5,
                              "column": 10
                            },
                            "end": {
                              "line": 5,
                              "column": 20
                            }
                          },
                          "name": "businessId"
                        },
                        "kind": "init",
                        "value": {
                          "type": "Identifier",
                          "start": 92,
                          "end": 102,
                          "loc": {
                            "start": {
                              "line": 5,
                              "column": 10
                            },
                            "end": {
                              "line": 5,
                              "column": 20
                            }
                          },
                          "name": "businessId"
                        }
                      }
                    ]
                  },
                  "init": {
                    "type": "MemberExpression",
                    "start": 107,
                    "end": 121,
                    "loc": {
                      "start": {
                        "line": 5,
                        "column": 25
                      },
                      "end": {
                        "line": 5,
                        "column": 39
                      }
                    },
                    "object": {
                      "type": "MemberExpression",
                      "start": 107,
                      "end": 116,
                      "loc": {
                        "start": {
                          "line": 5,
                          "column": 25
                        },
                        "end": {
                          "line": 5,
                          "column": 34
                        }
                      },
                      "object": {
                        "type": "Identifier",
                        "start": 107,
                        "end": 110,
                        "loc": {
                          "start": {
                            "line": 5,
                            "column": 25
                          },
                          "end": {
                            "line": 5,
                            "column": 28
                          }
                        },
                        "name": "ctx"
                      },
                      "property": {
                        "type": "Identifier",
                        "start": 111,
                        "end": 116,
                        "loc": {
                          "start": {
                            "line": 5,
                            "column": 29
                          },
                          "end": {
                            "line": 5,
                            "column": 34
                          }
                        },
                        "name": "state"
                      },
                      "computed": false
                    },
                    "property": {
                      "type": "Identifier",
                      "start": 117,
                      "end": 121,
                      "loc": {
                        "start": {
                          "line": 5,
                          "column": 35
                        },
                        "end": {
                          "line": 5,
                          "column": 39
                        }
                      },
                      "name": "user"
                    },
                    "computed": false
                  }
                }
              ],
              "kind": "const"
            },
            {
              "type": "TryStatement",
              "start": 126,
              "end": 371,
              "loc": {
                "start": {
                  "line": 7,
                  "column": 2
                },
                "end": {
                  "line": 18,
                  "column": 3
                }
              },
              "block": {
                "type": "BlockStatement",
                "start": 130,
                "end": 280,
                "loc": {
                  "start": {
                    "line": 7,
                    "column": 6
                  },
                  "end": {
                    "line": 14,
                    "column": 3
                  }
                },
                "body": [
                  {
                    "type": "ExpressionStatement",
                    "start": 136,
                    "end": 222,
                    "loc": {
                      "start": {
                        "line": 8,
                        "column": 4
                      },
                      "end": {
                        "line": 9,
                        "column": 41
                      }
                    },
                    "expression": {
                      "type": "AwaitExpression",
                      "start": 136,
                      "end": 221,
                      "loc": {
                        "start": {
                          "line": 8,
                          "column": 4
                        },
                        "end": {
                          "line": 9,
                          "column": 40
                        }
                      },
                      "all": false,
                      "argument": {
                        "type": "CallExpression",
                        "start": 142,
                        "end": 221,
                        "loc": {
                          "start": {
                            "line": 8,
                            "column": 10
                          },
                          "end": {
                            "line": 9,
                            "column": 40
                          }
                        },
                        "callee": {
                          "type": "MemberExpression",
                          "start": 142,
                          "end": 204,
                          "loc": {
                            "start": {
                              "line": 8,
                              "column": 10
                            },
                            "end": {
                              "line": 9,
                              "column": 23
                            }
                          },
                          "object": {
                            "type": "CallExpression",
                            "start": 142,
                            "end": 180,
                            "loc": {
                              "start": {
                                "line": 8,
                                "column": 10
                              },
                              "end": {
                                "line": 8,
                                "column": 48
                              }
                            },
                            "callee": {
                              "type": "MemberExpression",
                              "start": 142,
                              "end": 168,
                              "loc": {
                                "start": {
                                  "line": 8,
                                  "column": 10
                                },
                                "end": {
                                  "line": 8,
                                  "column": 36
                                }
                              },
                              "object": {
                                "type": "Identifier",
                                "start": 142,
                                "end": 150,
                                "loc": {
                                  "start": {
                                    "line": 8,
                                    "column": 10
                                  },
                                  "end": {
                                    "line": 8,
                                    "column": 18
                                  }
                                },
                                "name": "Business"
                              },
                              "property": {
                                "type": "Identifier",
                                "start": 151,
                                "end": 168,
                                "loc": {
                                  "start": {
                                    "line": 8,
                                    "column": 19
                                  },
                                  "end": {
                                    "line": 8,
                                    "column": 36
                                  }
                                },
                                "name": "findByIdAndRemove"
                              },
                              "computed": false
                            },
                            "arguments": [
                              {
                                "type": "Identifier",
                                "start": 169,
                                "end": 179,
                                "loc": {
                                  "start": {
                                    "line": 8,
                                    "column": 37
                                  },
                                  "end": {
                                    "line": 8,
                                    "column": 47
                                  }
                                },
                                "name": "businessId"
                              }
                            ]
                          },
                          "property": {
                            "type": "Identifier",
                            "start": 200,
                            "end": 204,
                            "loc": {
                              "start": {
                                "line": 9,
                                "column": 19
                              },
                              "end": {
                                "line": 9,
                                "column": 23
                              }
                            },
                            "name": "then"
                          },
                          "computed": false
                        },
                        "arguments": [
                          {
                            "type": "ArrowFunctionExpression",
                            "start": 205,
                            "end": 220,
                            "loc": {
                              "start": {
                                "line": 9,
                                "column": 24
                              },
                              "end": {
                                "line": 9,
                                "column": 39
                              }
                            },
                            "id": null,
                            "generator": false,
                            "expression": true,
                            "async": false,
                            "params": [
                              {
                                "type": "Identifier",
                                "start": 205,
                                "end": 206,
                                "loc": {
                                  "start": {
                                    "line": 9,
                                    "column": 24
                                  },
                                  "end": {
                                    "line": 9,
                                    "column": 25
                                  }
                                },
                                "name": "b"
                              }
                            ],
                            "body": {
                              "type": "CallExpression",
                              "start": 210,
                              "end": 220,
                              "loc": {
                                "start": {
                                  "line": 9,
                                  "column": 29
                                },
                                "end": {
                                  "line": 9,
                                  "column": 39
                                }
                              },
                              "callee": {
                                "type": "MemberExpression",
                                "start": 210,
                                "end": 218,
                                "loc": {
                                  "start": {
                                    "line": 9,
                                    "column": 29
                                  },
                                  "end": {
                                    "line": 9,
                                    "column": 37
                                  }
                                },
                                "object": {
                                  "type": "Identifier",
                                  "start": 210,
                                  "end": 211,
                                  "loc": {
                                    "start": {
                                      "line": 9,
                                      "column": 29
                                    },
                                    "end": {
                                      "line": 9,
                                      "column": 30
                                    }
                                  },
                                  "name": "b"
                                },
                                "property": {
                                  "type": "Identifier",
                                  "start": 212,
                                  "end": 218,
                                  "loc": {
                                    "start": {
                                      "line": 9,
                                      "column": 31
                                    },
                                    "end": {
                                      "line": 9,
                                      "column": 37
                                    }
                                  },
                                  "name": "remove"
                                },
                                "computed": false
                              },
                              "arguments": []
                            }
                          }
                        ]
                      }
                    }
                  },
                  {
                    "type": "ExpressionStatement",
                    "start": 228,
                    "end": 245,
                    "loc": {
                      "start": {
                        "line": 11,
                        "column": 4
                      },
                      "end": {
                        "line": 11,
                        "column": 21
                      }
                    },
                    "expression": {
                      "type": "AssignmentExpression",
                      "start": 228,
                      "end": 244,
                      "loc": {
                        "start": {
                          "line": 11,
                          "column": 4
                        },
                        "end": {
                          "line": 11,
                          "column": 20
                        }
                      },
                      "operator": "=",
                      "left": {
                        "type": "MemberExpression",
                        "start": 228,
                        "end": 238,
                        "loc": {
                          "start": {
                            "line": 11,
                            "column": 4
                          },
                          "end": {
                            "line": 11,
                            "column": 14
                          }
                        },
                        "object": {
                          "type": "Identifier",
                          "start": 228,
                          "end": 231,
                          "loc": {
                            "start": {
                              "line": 11,
                              "column": 4
                            },
                            "end": {
                              "line": 11,
                              "column": 7
                            }
                          },
                          "name": "ctx"
                        },
                        "property": {
                          "type": "Identifier",
                          "start": 232,
                          "end": 238,
                          "loc": {
                            "start": {
                              "line": 11,
                              "column": 8
                            },
                            "end": {
                              "line": 11,
                              "column": 14
                            }
                          },
                          "name": "status"
                        },
                        "computed": false
                      },
                      "right": {
                        "type": "Literal",
                        "start": 241,
                        "end": 244,
                        "loc": {
                          "start": {
                            "line": 11,
                            "column": 17
                          },
                          "end": {
                            "line": 11,
                            "column": 20
                          }
                        },
                        "value": 200,
                        "rawValue": 200,
                        "raw": "200"
                      }
                    }
                  },
                  {
                    "type": "ExpressionStatement",
                    "start": 250,
                    "end": 264,
                    "loc": {
                      "start": {
                        "line": 12,
                        "column": 4
                      },
                      "end": {
                        "line": 12,
                        "column": 18
                      }
                    },
                    "expression": {
                      "type": "AssignmentExpression",
                      "start": 250,
                      "end": 263,
                      "loc": {
                        "start": {
                          "line": 12,
                          "column": 4
                        },
                        "end": {
                          "line": 12,
                          "column": 17
                        }
                      },
                      "operator": "=",
                      "left": {
                        "type": "MemberExpression",
                        "start": 250,
                        "end": 258,
                        "loc": {
                          "start": {
                            "line": 12,
                            "column": 4
                          },
                          "end": {
                            "line": 12,
                            "column": 12
                          }
                        },
                        "object": {
                          "type": "Identifier",
                          "start": 250,
                          "end": 253,
                          "loc": {
                            "start": {
                              "line": 12,
                              "column": 4
                            },
                            "end": {
                              "line": 12,
                              "column": 7
                            }
                          },
                          "name": "ctx"
                        },
                        "property": {
                          "type": "Identifier",
                          "start": 254,
                          "end": 258,
                          "loc": {
                            "start": {
                              "line": 12,
                              "column": 8
                            },
                            "end": {
                              "line": 12,
                              "column": 12
                            }
                          },
                          "name": "body"
                        },
                        "computed": false
                      },
                      "right": {
                        "type": "ObjectExpression",
                        "start": 261,
                        "end": 263,
                        "loc": {
                          "start": {
                            "line": 12,
                            "column": 15
                          },
                          "end": {
                            "line": 12,
                            "column": 17
                          }
                        },
                        "properties": []
                      }
                    }
                  },
                  {
                    "type": "ReturnStatement",
                    "start": 269,
                    "end": 276,
                    "loc": {
                      "start": {
                        "line": 13,
                        "column": 4
                      },
                      "end": {
                        "line": 13,
                        "column": 11
                      }
                    },
                    "argument": null
                  }
                ]
              },
              "handler": {
                "type": "CatchClause",
                "start": 281,
                "end": 371,
                "loc": {
                  "start": {
                    "line": 14,
                    "column": 4
                  },
                  "end": {
                    "line": 18,
                    "column": 3
                  }
                },
                "param": {
                  "type": "Identifier",
                  "start": 288,
                  "end": 293,
                  "loc": {
                    "start": {
                      "line": 14,
                      "column": 11
                    },
                    "end": {
                      "line": 14,
                      "column": 16
                    }
                  },
                  "name": "error"
                },
                "body": {
                  "type": "BlockStatement",
                  "start": 295,
                  "end": 371,
                  "loc": {
                    "start": {
                      "line": 14,
                      "column": 18
                    },
                    "end": {
                      "line": 18,
                      "column": 3
                    }
                  },
                  "body": [
                    {
                      "type": "ExpressionStatement",
                      "start": 301,
                      "end": 318,
                      "loc": {
                        "start": {
                          "line": 15,
                          "column": 4
                        },
                        "end": {
                          "line": 15,
                          "column": 21
                        }
                      },
                      "expression": {
                        "type": "AssignmentExpression",
                        "start": 301,
                        "end": 317,
                        "loc": {
                          "start": {
                            "line": 15,
                            "column": 4
                          },
                          "end": {
                            "line": 15,
                            "column": 20
                          }
                        },
                        "operator": "=",
                        "left": {
                          "type": "MemberExpression",
                          "start": 301,
                          "end": 311,
                          "loc": {
                            "start": {
                              "line": 15,
                              "column": 4
                            },
                            "end": {
                              "line": 15,
                              "column": 14
                            }
                          },
                          "object": {
                            "type": "Identifier",
                            "start": 301,
                            "end": 304,
                            "loc": {
                              "start": {
                                "line": 15,
                                "column": 4
                              },
                              "end": {
                                "line": 15,
                                "column": 7
                              }
                            },
                            "name": "ctx"
                          },
                          "property": {
                            "type": "Identifier",
                            "start": 305,
                            "end": 311,
                            "loc": {
                              "start": {
                                "line": 15,
                                "column": 8
                              },
                              "end": {
                                "line": 15,
                                "column": 14
                              }
                            },
                            "name": "status"
                          },
                          "computed": false
                        },
                        "right": {
                          "type": "Literal",
                          "start": 314,
                          "end": 317,
                          "loc": {
                            "start": {
                              "line": 15,
                              "column": 17
                            },
                            "end": {
                              "line": 15,
                              "column": 20
                            }
                          },
                          "value": 500,
                          "rawValue": 500,
                          "raw": "500"
                        }
                      }
                    },
                    {
                      "type": "ExpressionStatement",
                      "start": 323,
                      "end": 355,
                      "loc": {
                        "start": {
                          "line": 16,
                          "column": 4
                        },
                        "end": {
                          "line": 16,
                          "column": 36
                        }
                      },
                      "expression": {
                        "type": "AssignmentExpression",
                        "start": 323,
                        "end": 354,
                        "loc": {
                          "start": {
                            "line": 16,
                            "column": 4
                          },
                          "end": {
                            "line": 16,
                            "column": 35
                          }
                        },
                        "operator": "=",
                        "left": {
                          "type": "MemberExpression",
                          "start": 323,
                          "end": 331,
                          "loc": {
                            "start": {
                              "line": 16,
                              "column": 4
                            },
                            "end": {
                              "line": 16,
                              "column": 12
                            }
                          },
                          "object": {
                            "type": "Identifier",
                            "start": 323,
                            "end": 326,
                            "loc": {
                              "start": {
                                "line": 16,
                                "column": 4
                              },
                              "end": {
                                "line": 16,
                                "column": 7
                              }
                            },
                            "name": "ctx"
                          },
                          "property": {
                            "type": "Identifier",
                            "start": 327,
                            "end": 331,
                            "loc": {
                              "start": {
                                "line": 16,
                                "column": 8
                              },
                              "end": {
                                "line": 16,
                                "column": 12
                              }
                            },
                            "name": "body"
                          },
                          "computed": false
                        },
                        "right": {
                          "type": "ObjectExpression",
                          "start": 334,
                          "end": 354,
                          "loc": {
                            "start": {
                              "line": 16,
                              "column": 15
                            },
                            "end": {
                              "line": 16,
                              "column": 35
                            }
                          },
                          "properties": [
                            {
                              "type": "Property",
                              "start": 336,
                              "end": 352,
                              "loc": {
                                "start": {
                                  "line": 16,
                                  "column": 17
                                },
                                "end": {
                                  "line": 16,
                                  "column": 33
                                }
                              },
                              "method": false,
                              "shorthand": false,
                              "computed": false,
                              "key": {
                                "type": "Identifier",
                                "start": 336,
                                "end": 341,
                                "loc": {
                                  "start": {
                                    "line": 16,
                                    "column": 17
                                  },
                                  "end": {
                                    "line": 16,
                                    "column": 22
                                  }
                                },
                                "name": "error"
                              },
                              "value": {
                                "type": "Literal",
                                "start": 343,
                                "end": 352,
                                "loc": {
                                  "start": {
                                    "line": 16,
                                    "column": 24
                                  },
                                  "end": {
                                    "line": 16,
                                    "column": 33
                                  }
                                },
                                "value": "no user",
                                "rawValue": "no user",
                                "raw": "\"no user\""
                              },
                              "kind": "init"
                            }
                          ]
                        }
                      }
                    },
                    {
                      "type": "ReturnStatement",
                      "start": 360,
                      "end": 367,
                      "loc": {
                        "start": {
                          "line": 17,
                          "column": 4
                        },
                        "end": {
                          "line": 17,
                          "column": 11
                        }
                      },
                      "argument": null
                    }
                  ]
                }
              },
              "guardedHandlers": [],
              "finalizer": null
            }
          ]
        },
        "leadingComments": [],
        "trailingComments": []
      },
      "specifiers": [],
      "source": null
    },
    {
      "type": "ExportDefaultDeclaration",
      "start": 376,
      "end": 395,
      "loc": {
        "start": {
          "line": 22,
          "column": 0
        },
        "end": {
          "line": 22,
          "column": 19
        }
      },
      "declaration": {
        "type": "Identifier",
        "start": 391,
        "end": 394,
        "loc": {
          "start": {
            "line": 22,
            "column": 15
          },
          "end": {
            "line": 22,
            "column": 18
          }
        },
        "name": "del",
        "leadingComments": [],
        "trailingComments": []
      }
    }
  ]
}